cornellGrading/__init__.py
cornellGrading/cornellGrading.py
cornellGrading/cornellInterface.py
cornellGrading/cornellQualtrics.py
cornellGrading/dueDatesFromCSV.py
cornellGrading/pandocHTMLParser.py
cornellGrading/upload_MC_questions.py
cornellGrading/utils.py
cornellgrading-2.24.0.data/scripts/canvastex.py
cornellgrading-2.24.0.data/scripts/matlabgrader.py
cornellgrading-2.24.0.data/scripts/setupSelfGrading.py
cornellgrading-2.24.0.dist-info/LICENSE
cornellgrading-2.24.0.dist-info/METADATA
cornellgrading-2.24.0.dist-info/WHEEL
cornellgrading-2.24.0.dist-info/entry_points.txt
cornellgrading-2.24.0.dist-info/top_level.txt
cornellgrading-2.24.0.dist-info/RECORD
