Metadata-Version: 2.1
Name: cornellGrading
Version: 2.24.0
Summary: Routines for interacting with Cornell installations of Canvas and Qualtrics
Home-page: https://github.com/dsavransky/grading
Author: Dmitry Savransky
Author-email: ds264@cornell.edu
License: MIT
Classifier: Programming Language :: Python :: 3.7
Classifier: Programming Language :: Python :: 3.8
Classifier: License :: OSI Approved :: MIT License
Classifier: Operating System :: OS Independent
Requires-Python: >=3.7
License-File: LICENSE
Requires-Dist: requests
Requires-Dist: numpy
Requires-Dist: pandas
Requires-Dist: keyring
Requires-Dist: canvasapi
Requires-Dist: pytz
Provides-Extra: interface
Requires-Dist: bullet; (platform_system == "Linux" or platform_system == "Darwin") and extra == "interface"
Requires-Dist: console-menu; platform_system == "Windows" and extra == "interface"
Provides-Extra: latex2html
Requires-Dist: pdf2image; extra == "latex2html"
Requires-Dist: Pillow; extra == "latex2html"
